{\n  \"sector\": \"MONJARVIREDCORE\",\n  \"descripcion\": {\n    \"metafora\": [\n      \"No es madera, es estructura comprimida.\",\n      \"No es peso, es libertad encapsulada.\",\n      \"No es un mueble, es un nodo portátil.\"\n    ],\n    \"concepto\": \"unidaddealmacenamientofisicouniversal\"\n  },\n  \"identidad\": {\n    \"id\": \"MONJARVIREDCORE\",\n    \"color_hex\": \"#FF0000\",\n    \"estetica\": \"cyberpunk_terminal\",\n    \"modo\": \"diseño_nómada\"\n  },\n  \"estados\": {\n    \"plegada\": \"formato_maleta\",\n    \"desplegada\": \"modulo_multiuso\"\n  },\n  \"funciones\": [\n    \"superficiedetrabajo\",\n    \"modulodealmacenaje\",\n    \"nodoespacialportatil\"\n  ],\n  \"especificaciones\": {\n    \"peso\": \"optimizadoparamovilidad\",\n    \"ensamblaje\": \"sin_herramientas\",\n    \"resistencia\": \"alta\",\n    \"mantenimiento\": \"minimo\"\n  },\n  \"mensaje_final\": \"La mina ya no tiene dueño, porque el dueño lleva la mina consigo.\"\n}